{
  "version": "1.1.0",
  "flags": {},
  "shapes": [
    {
      "label": "book",
      "text": "",
      "points": [
        [
          746.4761904761905,
          299.1428571428571
        ],
        [
          865.5238095238095,
          4008.6666666666665
        ],
        [
          1036.9523809523807,
          3984.857142857143
        ],
        [
          917.9047619047618,
          303.90476190476187
        ]
      ],
      "group_id": null,
      "shape_type": "polygon",
      "flags": {}
    },
    {
      "label": "book",
      "text": "",
      "points": [
        [
          941.7142857142857,
          322.9523809523809
        ],
        [
          1051.2380952380954,
          3999.1428571428573
        ],
        [
          1308.3809523809523,
          3999.1428571428573
        ],
        [
          1203.6190476190473,
          313.4285714285714
        ]
      ],
      "group_id": null,
      "shape_type": "polygon",
      "flags": {}
    },
    {
      "label": "book",
      "text": "",
      "points": [
        [
          1227.428571428571,
          318.19047619047615
        ],
        [
          1336.9523809523807,
          4003.904761904762
        ],
        [
          1465.5238095238092,
          4003.904761904762
        ],
        [
          1379.8095238095239,
          318.19047619047615
        ]
      ],
      "group_id": null,
      "shape_type": "polygon",
      "flags": {}
    },
    {
      "label": "book",
      "text": "",
      "points": [
        [
          1422.6666666666665,
          346.7619047619047
        ],
        [
          1498.8571428571427,
          3999.1428571428573
        ],
        [
          1684.5714285714284,
          3989.6190476190477
        ],
        [
          1603.6190476190473,
          346.7619047619047
        ]
      ],
      "group_id": null,
      "shape_type": "polygon",
      "flags": {}
    },
    {
      "label": "book",
      "text": "",
      "points": [
        [
          1617.904761904762,
          351.52380952380946
        ],
        [
          1698.8571428571427,
          3999.1428571428573
        ],
        [
          1908.3809523809523,
          3994.3809523809523
        ],
        [
          1841.7142857142858,
          351.52380952380946
        ]
      ],
      "group_id": null,
      "shape_type": "polygon",
      "flags": {}
    },
    {
      "label": "book",
      "text": "",
      "points": [
        [
          1879.8095238095239,
          365.8095238095238
        ],
        [
          1932.1904761904761,
          3994.3809523809523
        ],
        [
          2156.0,
          3989.6190476190477
        ],
        [
          2089.333333333333,
          356.2857142857143
        ]
      ],
      "group_id": null,
      "shape_type": "polygon",
      "flags": {}
    },
    {
      "label": "book",
      "text": "",
      "points": [
        [
          2141.714285714286,
          380.0952380952381
        ],
        [
          2179.809523809524,
          3980.095238095238
        ],
        [
          2389.333333333333,
          3994.3809523809523
        ],
        [
          2356.0,
          370.57142857142856
        ]
      ],
      "group_id": null,
      "shape_type": "polygon",
      "flags": {}
    },
    {
      "label": "book",
      "text": "",
      "points": [
        [
          2384.5714285714284,
          399.1428571428571
        ],
        [
          2417.904761904762,
          3984.857142857143
        ],
        [
          2584.5714285714284,
          3980.095238095238
        ],
        [
          2541.714285714286,
          403.90476190476187
        ]
      ],
      "group_id": null,
      "shape_type": "polygon",
      "flags": {}
    },
    {
      "label": "book",
      "text": "",
      "points": [
        [
          2579.809523809524,
          422.9523809523809
        ],
        [
          2608.3809523809523,
          3980.095238095238
        ],
        [
          2960.7619047619046,
          3975.3333333333335
        ],
        [
          2936.9523809523807,
          413.4285714285714
        ]
      ],
      "group_id": null,
      "shape_type": "polygon",
      "flags": {}
    },
    {
      "label": "book",
      "text": "",
      "points": [
        [
          2994.095238095238,
          403.90476190476187
        ],
        [
          2989.333333333333,
          3989.6190476190477
        ],
        [
          3217.904761904762,
          3999.1428571428573
        ],
        [
          3222.6666666666665,
          403.90476190476187
        ]
      ],
      "group_id": null,
      "shape_type": "polygon",
      "flags": {}
    },
    {
      "label": "book",
      "text": "",
      "points": [
        [
          3241.714285714286,
          408.66666666666663
        ],
        [
          3255.9999999999995,
          3975.3333333333335
        ],
        [
          3446.4761904761904,
          3989.6190476190477
        ],
        [
          3451.238095238095,
          399.1428571428571
        ]
      ],
      "group_id": null,
      "shape_type": "polygon",
      "flags": {}
    },
    {
      "label": "book",
      "text": "",
      "points": [
        [
          3475.047619047619,
          389.6190476190476
        ],
        [
          3455.9999999999995,
          3984.857142857143
        ],
        [
          3622.6666666666665,
          3999.1428571428573
        ],
        [
          3636.952380952381,
          384.85714285714283
        ]
      ],
      "group_id": null,
      "shape_type": "polygon",
      "flags": {}
    },
    {
      "label": "book",
      "text": "",
      "points": [
        [
          3651.238095238095,
          432.4761904761904
        ],
        [
          3632.1904761904757,
          3984.857142857143
        ],
        [
          3803.6190476190473,
          3984.857142857143
        ],
        [
          3836.952380952381,
          427.71428571428567
        ]
      ],
      "group_id": null,
      "shape_type": "polygon",
      "flags": {}
    },
    {
      "label": "book",
      "text": "",
      "points": [
        [
          3860.761904761905,
          742.0
        ],
        [
          3817.904761904762,
          3984.857142857143
        ],
        [
          4027.428571428571,
          3980.095238095238
        ],
        [
          4065.5238095238096,
          742.0
        ]
      ],
      "group_id": null,
      "shape_type": "polygon",
      "flags": {}
    },
    {
      "label": "book",
      "text": "",
      "points": [
        [
          4089.3333333333335,
          761.047619047619
        ],
        [
          4046.4761904761904,
          3999.1428571428573
        ],
        [
          4284.571428571429,
          4022.952380952381
        ],
        [
          4332.190476190476,
          765.8095238095239
        ]
      ],
      "group_id": null,
      "shape_type": "polygon",
      "flags": {}
    },
    {
      "label": "book",
      "text": "",
      "points": [
        [
          4389.333333333334,
          742.0
        ],
        [
          4332.190476190476,
          770.5714285714286
        ],
        [
          4294.0952380952385,
          3999.1428571428573
        ],
        [
          4327.428571428572,
          4042.0000000000005
        ],
        [
          4551.238095238095,
          4051.5238095238096
        ],
        [
          4613.142857142858,
          746.7619047619048
        ]
      ],
      "group_id": null,
      "shape_type": "polygon",
      "flags": {}
    },
    {
      "label": "book",
      "text": "",
      "points": [
        [
          4641.714285714286,
          765.8095238095239
        ],
        [
          4565.52380952381,
          4022.952380952381
        ],
        [
          4779.809523809524,
          4013.4285714285716
        ],
        [
          4865.52380952381,
          746.7619047619048
        ]
      ],
      "group_id": null,
      "shape_type": "polygon",
      "flags": {}
    },
    {
      "label": "book",
      "text": "",
      "points": [
        [
          4908.380952380953,
          722.952380952381
        ],
        [
          4865.52380952381,
          746.7619047619048
        ],
        [
          4794.0952380952385,
          3980.095238095238
        ],
        [
          4836.952380952382,
          4008.6666666666665
        ],
        [
          5008.380952380953,
          4003.904761904762
        ],
        [
          5098.857142857143,
          718.1904761904763
        ]
      ],
      "group_id": null,
      "shape_type": "polygon",
      "flags": {}
    }
  ],
  "imagePath": "..\\images\\1.jpg",
  "imageData": null,
  "imageHeight": 4284,
  "imageWidth": 5712
}